burst2safe/__init__.py
burst2safe/auth.py
burst2safe/base.py
burst2safe/burst2safe.py
burst2safe/burst2stack.py
burst2safe/burst_id.py
burst2safe/calibration.py
burst2safe/download.py
burst2safe/local2safe.py
burst2safe/manifest.py
burst2safe/measurement.py
burst2safe/noise.py
burst2safe/product.py
burst2safe/rfi.py
burst2safe/safe.py
burst2safe/search.py
burst2safe/swath.py
burst2safe/utils.py
burst2safe/data/logo.png
burst2safe/data/support_236/s1-level-1-calibration.xsd
burst2safe/data/support_236/s1-level-1-measurement.xsd
burst2safe/data/support_236/s1-level-1-noise.xsd
burst2safe/data/support_236/s1-level-1-product.xsd
burst2safe/data/support_236/s1-level-1-quicklook.xsd
burst2safe/data/support_236/s1-map-overlay.xsd
burst2safe/data/support_236/s1-object-types.xsd
burst2safe/data/support_236/s1-product-preview.xsd
burst2safe/data/support_243/s1-level-1-calibration.xsd
burst2safe/data/support_243/s1-level-1-measurement.xsd
burst2safe/data/support_243/s1-level-1-noise.xsd
burst2safe/data/support_243/s1-level-1-product.xsd
burst2safe/data/support_243/s1-level-1-quicklook.xsd
burst2safe/data/support_243/s1-map-overlay.xsd
burst2safe/data/support_243/s1-object-types.xsd
burst2safe/data/support_243/s1-product-preview.xsd
burst2safe/data/support_260/s1-level-1-calibration.xsd
burst2safe/data/support_260/s1-level-1-measurement.xsd
burst2safe/data/support_260/s1-level-1-noise.xsd
burst2safe/data/support_260/s1-level-1-product.xsd
burst2safe/data/support_260/s1-level-1-quicklook.xsd
burst2safe/data/support_260/s1-map-overlay.xsd
burst2safe/data/support_260/s1-object-types.xsd
burst2safe/data/support_260/s1-product-preview.xsd
burst2safe/data/support_290/s1-level-1-calibration.xsd
burst2safe/data/support_290/s1-level-1-measurement.xsd
burst2safe/data/support_290/s1-level-1-noise.xsd
burst2safe/data/support_290/s1-level-1-product.xsd
burst2safe/data/support_290/s1-level-1-quicklook.xsd
burst2safe/data/support_290/s1-map-overlay.xsd
burst2safe-2.0.2.dist-info/licenses/LICENSE
burst2safe-2.0.2.dist-info/METADATA
burst2safe-2.0.2.dist-info/WHEEL
burst2safe-2.0.2.dist-info/entry_points.txt
burst2safe-2.0.2.dist-info/top_level.txt
burst2safe-2.0.2.dist-info/RECORD
