Metadata-Version: 2.4
Name: burst2safe
Version: 2.0.2
Summary: A package for converting ASF-derived Sentinel-1 burst SLC products to the ESA SAFE format
Author-email: Forrest Williams <ffwilliams2@alaska.edu>
Maintainer-email: ASF APD/Tools Team <uaf-asf-apd@alaska.edu>
Project-URL: Homepage, https://github.com/ASFHyP3/burst2safe
Project-URL: Bug Tracker, https://github.com/ASFHyP3/burst2safe/issues
Classifier: Intended Audience :: Science/Research
Classifier: Natural Language :: English
Classifier: Operating System :: OS Independent
Classifier: Programming Language :: Python :: 3
Classifier: Programming Language :: Python :: 3.10
Classifier: Programming Language :: Python :: 3.11
Classifier: Programming Language :: Python :: 3.12
Classifier: Programming Language :: Python :: 3.13
Requires-Python: >=3.10
License-File: LICENSE
Requires-Dist: gdal
Requires-Dist: shapely>=2.1.0
Requires-Dist: numpy
Requires-Dist: lxml
Requires-Dist: tifffile>=2022.04.22
Requires-Dist: asf_search
Requires-Dist: dateparser!=1.1.0
Requires-Dist: aiohttp>=3.12.6
Provides-Extra: develop
Requires-Dist: pytest; extra == "develop"
Dynamic: license-file
